asgi_tus/__init__.py
asgi_tus/config.py
asgi_tus/core.py
asgi_tus/examples.py
asgi_tus/storage.py
asgi_tus/utils.py
asgi_tus/integrations/__init__.py
asgi_tus/integrations/fastapi.py
asgi_tus/integrations/starlette.py
asgi_tus/tests/__init__.py
asgi_tus/tests/conftest.py
asgi_tus/tests/test_comprehensive.py
asgi_tus-0.1.0.dist-info/METADATA
asgi_tus-0.1.0.dist-info/WHEEL
asgi_tus-0.1.0.dist-info/entry_points.txt
asgi_tus-0.1.0.dist-info/RECORD
