Metadata-Version: 2.4
Name: asgi-tus
Version: 0.1.0
Summary: A Python ASGI implementation of the tus resumable upload protocol with FastAPI and Starlette integrations.
Project-URL: Homepage, https://github.com/notdaniel/asgi-tus
Project-URL: Repository, https://github.com/notdaniel/asgi-tus
Project-URL: Issues, https://github.com/notdaniel/asgi-tus/issues
Project-URL: Documentation, https://github.com/notdaniel/asgi-tus#readme
Author-email: Daniel Keywan Hollister <daniel.hollister@gmail.com>
License: MIT
Keywords: asgi,fastapi,resumable,starlette,tus,upload
Classifier: Development Status :: 4 - Beta
Classifier: Framework :: AsyncIO
Classifier: Framework :: FastAPI
Classifier: Intended Audience :: Developers
Classifier: License :: OSI Approved :: MIT License
Classifier: Programming Language :: Python :: 3
Classifier: Programming Language :: Python :: 3.12
Classifier: Programming Language :: Python :: 3.13
Classifier: Programming Language :: Python :: 3.14
Classifier: Topic :: Internet :: WWW/HTTP :: HTTP Servers
Classifier: Topic :: Software Development :: Libraries :: Python Modules
Requires-Python: >=3.12
Requires-Dist: aiofiles>=24.1.0
Requires-Dist: orjson>=3.11.1
Requires-Dist: structlog>=25.4.0
Provides-Extra: all
Requires-Dist: fastapi[standard]>=0.116.1; extra == 'all'
Requires-Dist: starlette[full]>=0.47.2; extra == 'all'
Requires-Dist: uvicorn[standard]>=0.35.0; extra == 'all'
Provides-Extra: fastapi
Requires-Dist: fastapi[standard]>=0.116.1; extra == 'fastapi'
Provides-Extra: server
Requires-Dist: uvicorn[standard]>=0.35.0; extra == 'server'
Provides-Extra: starlette
Requires-Dist: starlette[full]>=0.47.2; extra == 'starlette'
